samson
samson/ace
samson/analysis
samson/analyzers
samson/attacks
samson/auxiliary
samson/block_ciphers
samson/block_ciphers/modes
samson/classical
samson/constructions
samson/core
samson/encoding
samson/encoding/dns_key
samson/encoding/jwk
samson/encoding/openssh
samson/encoding/openssh/core
samson/encoding/pkcs1
samson/encoding/pkcs8
samson/encoding/x509
samson/hashes
samson/kdfs
samson/macs
samson/math
samson/math/algebra
samson/math/algebra/curves
samson/math/algebra/fields
samson/math/algebra/rings
samson/math/factorization
samson/oracles
samson/padding
samson/prngs
samson/protocols
samson/protocols/jwt
samson/public_key
samson/stream_ciphers
samson/utilities
