Metadata-Version: 2.1
Name: samson-crypto
Version: 0.2.4
Summary: Cryptanalysis and attack library
Home-page: https://github.com/wildcardcorp/samson
Author: Daniel Cronce
Author-email: daniel.cronce@wildcardcorp.com
License: UNKNOWN
Keywords: cryptography security cryptanalysis
Platform: UNKNOWN
Classifier: Topic :: Security
Classifier: Topic :: Security :: Cryptography
Classifier: Topic :: Scientific/Engineering
Classifier: Topic :: Scientific/Engineering :: Mathematics
Classifier: Programming Language :: Python :: 3
Classifier: Programming Language :: Python :: 3.6
Classifier: Programming Language :: Python :: Implementation :: CPython
Classifier: Programming Language :: Python :: Implementation :: PyPy
